normcall/__init__.py
normcall/__main__.py
normcall/core/__init__.py
normcall/tests/__init__.py
normcall/tests/test_1984.py
normcall-0.0.0.dev0.dist-info/licenses/LICENSE.txt
normcall-0.0.0.dev0.dist-info/METADATA
normcall-0.0.0.dev0.dist-info/WHEEL
normcall-0.0.0.dev0.dist-info/top_level.txt
normcall-0.0.0.dev0.dist-info/RECORD
